pop_ml/conf.py
pop_ml/scripts.py
pop_ml/version.py
pop_ml/ml/dataset.py
pop_ml/ml/init.py
pop_ml/ml/tokenizer.py
pop_ml/token/init.py
pop_ml/token/python_keywords.py
pop_ml/token/contracts/init.py
pop_ml-0.2.0.dist-info/LICENSE
pop_ml-0.2.0.dist-info/METADATA
pop_ml-0.2.0.dist-info/WHEEL
pop_ml-0.2.0.dist-info/entry_points.txt
pop_ml-0.2.0.dist-info/top_level.txt
pop_ml-0.2.0.dist-info/RECORD
