Metadata-Version: 2.1
Name: pop-ml
Version: 0.2.0
Summary: Machine learning library for pop projects
Home-page: https://vmware.gitlab.io/pop/pop-ml/en/latest/index.html
Author: VMWare, Inc.
Author-email: idemproject@vmware.com
License: Apache Software License 2.0
Project-URL: Code, https://gitlab.com/vmware/pop/pop-ml
Project-URL: Issue tracker, https://gitlab.com/vmware/pop/pop-ml/issues
Platform: UNKNOWN
Classifier: Topic :: Scientific/Engineering :: Artificial Intelligence
Classifier: Environment :: Console
Classifier: Intended Audience :: Developers
Classifier: Intended Audience :: Information Technology
Classifier: Intended Audience :: System Administrators
Classifier: Operating System :: OS Independent
Classifier: Programming Language :: Python
Classifier: Programming Language :: Python :: 3.8
Classifier: Programming Language :: Python :: 3.9
Classifier: Programming Language :: Python :: 3.10
Classifier: Programming Language :: Python :: 3.11
Classifier: Development Status :: 3 - Alpha
Classifier: License :: OSI Approved :: Apache Software License
Requires-Python: >=3.8
License-File: LICENSE
Requires-Dist: pop (>=23.1.0)
Requires-Dist: transformers
Requires-Dist: torch
Requires-Dist: sentencepiece
Requires-Dist: sacremoses
Requires-Dist: datasets
